Workbook

Sheet 見積書
A1: 御見積書
F2: 御見積日
A3: お客様名 | B3: =[1]顧客名簿!$B$3 -> 岩田 稔 | F3: 大平自動車商会
A4: ご 住 所 | B4: =[1]顧客名簿!$B$6 -> 山口県下関市長府安養寺 | F4: 〒751-0804
B5: =[1]顧客名簿!$B$7 -> １丁目13-27 | F5: 下関市楠乃町5丁目９番
A6: T E L | B6: =[1]顧客名簿!$B$8 -> 080-6315-5625 | F6: TEL083-257-0101
F7: FAX083-257-0202
A8: 車名 | B8: =[1]顧客名簿!$D$4 -> 三菱EK | F8: 登録番号T7-8106-7609-0169
A9: 型式・年式 | B9: =[1]顧客名簿!$D$7 -> 15409 | F9: 振込口座 西中国信用金庫
A10: ナンバー | B10: =[1]顧客名簿!$D$5 -> 下関580こ1533 | F10: 一の宮支店 普通 0341746
A11: 車台番号 | B11: =[1]顧客名簿!$D$6 -> H82W-1350882 | F11: 大平自動車商会 ｵｵﾋﾗ ﾋﾃﾞｱｷ
A13: お見積金額 | B13: =G38 -> 0
A15: 商品名 | B15: 適用 | C15: 数量 | D15: 単価(税抜） | E15: 消費税率 | F15: 税額 | G15: 金額(税抜)
F16: =C16*D16*E16 -> 0 | G16: =D16*C16 -> 0
F17: =C17*D17*E17 -> 0 | G17: =D17*C17 -> 0
F18: =C18*D18*E18 -> 0 | G18: =D18*C18 -> 0
F19: =C19*D19*E19 -> 0 | G19: =D19*C19 -> 0
F20: =C20*D20*E20 -> 0 | G20: =D20*C20 -> 0
F21: =C21*D21*E21 -> 0 | G21: =D21*C21 -> 0
F22: =C22*D22*E22 -> 0 | G22: =D22*C22 -> 0
F23: =C23*D23*E23 -> 0 | G23: =D23*C23 -> 0
F24: =C24*D24*E24 -> 0 | G24: =D24*C24 -> 0
F25: =C25*D25*E25 -> 0 | G25: =D25*C25 -> 0
F26: =C26*D26*E26 -> 0 | G26: =D26*C26 -> 0
F27: =C27*D27*E27 -> 0 | G27: =D27*C27 -> 0
... F35: =C35*D35*E35 -> 0 | G35: =D35*C35 -> 0
A36: ※ｵｰﾀﾞｰ商品は返品できない場合があります。 | E36: 商品代金 | G36: =SUM(G16:H35) -> 0
E37: 消費税(10％) | G37: =SUM(F16:F35) -> 0
E38: 合計 | G38: =SUM(G36:H37) -> 0

Sheet 請求書
A1: 御請求書
F2: 御請求日 | G2: =見積書!G2 -> 0
A3: お客様名 | B3: =[1]顧客名簿!$B$3 -> 岩田 稔 | F3: 大平自動車商会
A4: ご 住 所 | B4: =[1]顧客名簿!$B$6 -> 山口県下関市長府安養寺 | F4: 〒751-0804
B5: =[1]顧客名簿!$B$7 -> １丁目13-27 | F5: 下関市楠乃町5丁目９番
A6: T E L | B6: =[1]顧客名簿!$B$8 -> 080-6315-5625 | F6: TEL083-257-0101
F7: FAX083-257-0202
A8: 車名 | B8: =[1]顧客名簿!$D$4 -> 三菱EK | F8: 登録番号T7-8106-7609-0169
A9: 型式・年式 | B9: =[1]顧客名簿!$D$7 -> 15409 | F9: 振込口座 西中国信用金庫
A10: ナンバー | B10: =[1]顧客名簿!$D$5 -> 下関580こ1533 | F10: 一の宮支店 普通 0341746
A11: 車台番号 | B11: =[1]顧客名簿!$D$6 -> H82W-1350882 | F11: 大平自動車商会 ｵｵﾋﾗ ﾋﾃﾞｱｷ
A13: ご請求金額 | B13: =G38 -> 0
A15: 商品名 | B15: 適用 | C15: 数量 | D15: 単価(税抜） | E15: 消費税率 | F15: 税額 | G15: 金額(税抜)
A16: =IF(見積書!A16="","",見積書!A16) | B16: =IF(見積書!B16="","",見積書!B16) | C16: =IF(見積書!C16="","",見積書!C16) | D16: =IF(見積書!D16="","",見積書!D16) | E16: =IF(見積書!E16="","",見積書!E16) | F16: =IF(D16="","",C16*D16*E16) | G16: =IF(D16="","",D16*C16)
A17: =IF(見積書!A17="","",見積書!A17) | B17: =IF(見積書!B17="","",見積書!B17) | C17: =IF(見積書!C17="","",見積書!C17) | D17: =IF(見積書!D17="","",見積書!D17) | E17: =IF(見積書!E17="","",見積書!E17) | F17: =IF(D17="","",C17*D17*E17) | G17: =IF(D17="","",D17*C17)
A18: =IF(見積書!A18="","",見積書!A18) | B18: =IF(見積書!B18="","",見積書!B18) | C18: =IF(見積書!C18="","",見積書!C18) | D18: =IF(見積書!D18="","",見積書!D18) | E18: =IF(見積書!E18="","",見積書!E18) | F18: =IF(D18="","",C18*D18*E18) | G18: =IF(D18="","",D18*C18)
A19: =IF(見積書!A19="","",見積書!A19) | B19: =IF(見積書!B19="","",見積書!B19) | C19: =IF(見積書!C19="","",見積書!C19) | D19: =IF(見積書!D19="","",見積書!D19) | E19: =IF(見積書!E19="","",見積書!E19) | F19: =IF(D19="","",C19*D19*E19) | G19: =IF(D19="","",D19*C19)
A20: =IF(見積書!A20="","",見積書!A20) | B20: =IF(見積書!B20="","",見積書!B20) | C20: =IF(見積書!C20="","",見積書!C20) | D20: =IF(見積書!D20="","",見積書!D20) | E20: =IF(見積書!E20="","",見積書!E20) | F20: =IF(D20="","",C20*D20*E20) | G20: =IF(D20="","",D20*C20)
A21: =IF(見積書!A21="","",見積書!A21) | B21: =IF(見積書!B21="","",見積書!B21) | C21: =IF(見積書!C21="","",見積書!C21) | D21: =IF(見積書!D21="","",見積書!D21) | E21: =IF(見積書!E21="","",見積書!E21) | F21: =IF(D21="","",C21*D21*E21) | G21: =IF(D21="","",D21*C21)
A22: =IF(見積書!A22="","",見積書!A22) | B22: =IF(見積書!B22="","",見積書!B22) | C22: =IF(見積書!C22="","",見積書!C22) | D22: =IF(見積書!D22="","",見積書!D22) | E22: =IF(見積書!E22="","",見積書!E22) | F22: =IF(D22="","",C22*D22*E22) | G22: =IF(D22="","",D22*C22)
A23: =IF(見積書!A23="","",見積書!A23) | B23: =IF(見積書!B23="","",見積書!B23) | C23: =IF(見積書!C23="","",見積書!C23) | D23: =IF(見積書!D23="","",見積書!D23) | E23: =IF(見積書!E23="","",見積書!E23) | F23: =IF(D23="","",C23*D23*E23) | G23: =IF(D23="","",D23*C23)
A24: =IF(見積書!A24="","",見積書!A24) | B24: =IF(見積書!B24="","",見積書!B24) | C24: =IF(見積書!C24="","",見積書!C24) | D24: =IF(見積書!D24="","",見積書!D24) | E24: =IF(見積書!E24="","",見積書!E24) | F24: =IF(D24="","",C24*D24*E24) | G24: =IF(D24="","",D24*C24)
A25: =IF(見積書!A25="","",見積書!A25) | B25: =IF(見積書!B25="","",見積書!B25) | C25: =IF(見積書!C25="","",見積書!C25) | D25: =IF(見積書!D25="","",見積書!D25) | E25: =IF(見積書!E25="","",見積書!E25) | F25: =IF(D25="","",C25*D25*E25) | G25: =IF(D25="","",D25*C25)
A26: =IF(見積書!A26="","",見積書!A26) | B26: =IF(見積書!B26="","",見積書!B26) | C26: =IF(見積書!C26="","",見積書!C26) | D26: =IF(見積書!D26="","",見積書!D26) | E26: =IF(見積書!E26="","",見積書!E26) | F26: =IF(D26="","",C26*D26*E26) | G26: =IF(D26="","",D26*C26)
A27: =IF(見積書!A27="","",見積書!A27) | B27: =IF(見積書!B27="","",見積書!B27) | C27: =IF(見積書!C27="","",見積書!C27) | D27: =IF(見積書!D27="","",見積書!D27) | E27: =IF(見積書!E27="","",見積書!E27) | F27: =IF(D27="","",C27*D27*E27) | G27: =IF(D27="","",D27*C27)
... A35: =IF(見積書!A35="","",見積書!A35) | B35: =IF(見積書!B35="","",見積書!B35) | C35: =IF(見積書!C35="","",見積書!C35) | D35: =IF(見積書!D35="","",見積書!D35) | E35: =IF(見積書!E35="","",見積書!E35) | F35: =IF(D35="","",C35*D35*E35) | G35: =IF(D35="","",D35*C35)
A36: ※ｵｰﾀﾞｰ商品は返品できない場合があります。 | E36: 商品代金 | G36: =SUM(G16:H35) -> 0
E37: 消費税(10％) | G37: =SUM(F16:F35) -> 0
E38: 合計 | G38: =SUM(G36:H37) -> 0

Sheet 売上集計用
A1: 御請求日 | B1: お客様名 | C1: 住所1 | D1: 住所2 | E1: T E L | F1: 車名 | G1: 型式・年式 | H1: ナンバー | I1: 車台番号 | J1: 商品代金 | K1: 消費税(10％) | L1: ご請求金額
A2: =請求書!G2 -> 0 | B2: =請求書!B3 -> 岩田 稔 | C2: =請求書!B4 -> 山口県下関市長府安養寺 | D2: =請求書!B5 -> １丁目13-27 | E2: =請求書!B6 -> 080-6315-5625 | F2: =請求書!B8 -> 三菱EK | G2: =請求書!B9 -> 15409 | H2: =請求書!B10 -> 下関580こ1533 | I2: =請求書!B11 -> H82W-1350882 | J2: =請求書!G36 -> 0 | K2: =請求書!G37 -> 0 | L2: =請求書!G38 -> 0
