Workbook

Sheet 見積書
A1: 御見積書
F2: 御見積日
A3: お客様名 | B3: =[1]顧客名簿!$B$3 -> 山本 剛 | F3: 大平自動車商会
A4: ご 住 所 | B4: =[1]顧客名簿!$B$6 -> 山口県下関市田倉 | F4: 〒751-0804
B5: =[1]顧客名簿!$B$7 -> 125-5 | F5: 下関市楠乃町5丁目９番
A6: T E L | B6: =[1]顧客名簿!$B$8 -> 090-9061-7286 | F6: TEL083-257-0101
F7: FAX083-257-0202
A8: 車名 | B8: =[1]顧客名簿!$D$4 -> スズキエヴリィ
A9: 型式・年式 | B9: =[1]顧客名簿!$D$7 -> 15133
A10: ナンバー | B10: =[1]顧客名簿!$D$5 -> 下関580り7
A11: 車台番号 | B11: =[1]顧客名簿!$D$6 -> DA64W-248979
A13: ご請求金額 | B13: =G38 -> 0
A15: 商品名 | B15: 適用 | C15: 数量 | D15: 単価(税抜） | E15: 消費税率 | F15: 税額 | G15: 金額(税抜)
F16: =C16*D16*E16 -> 0 | G16: =D16*C16 -> 0
F17: =C17*D17*E17 -> 0 | G17: =D17*C17 -> 0
F18: =C18*D18*E18 -> 0 | G18: =D18*C18 -> 0
F19: =C19*D19*E19 -> 0 | G19: =D19*C19 -> 0
F20: =C20*D20*E20 -> 0 | G20: =D20*C20 -> 0
F21: =C21*D21*E21 -> 0 | G21: =D21*C21 -> 0
F22: =C22*D22*E22 -> 0 | G22: =D22*C22 -> 0
F23: =C23*D23*E23 -> 0 | G23: =D23*C23 -> 0
F24: =C24*D24*E24 -> 0 | G24: =D24*C24 -> 0
F25: =C25*D25*E25 -> 0 | G25: =D25*C25 -> 0
F26: =C26*D26*E26 -> 0 | G26: =D26*C26 -> 0
F27: =C27*D27*E27 -> 0 | G27: =D27*C27 -> 0
... F35: =C35*D35*E35 -> 0 | G35: =D35*C35 -> 0
A36: ※ｵｰﾀﾞｰ商品は返品できない場合があります。 | E36: 商品代金 | G36: =SUM(G16:H35) -> 0
E37: 消費税(10％) | G37: =SUM(F16:F35) -> 0
E38: 合計 | G38: =SUM(G36:H37) -> 0

Sheet 請求書
A1: 御請求書
F2: 御請求日 | G2: =見積書!G2 -> 0
A3: お客様名 | B3: =[1]顧客名簿!$B$3 -> 山本 剛 | F3: 大平自動車商会
A4: ご 住 所 | B4: =[1]顧客名簿!$B$6 -> 山口県下関市田倉 | F4: 〒751-0804
B5: =[1]顧客名簿!$B$7 -> 125-5 | F5: 下関市楠乃町5丁目９番
A6: T E L | B6: =[1]顧客名簿!$B$8 -> 090-9061-7286 | F6: TEL083-257-0101
F7: FAX083-257-0202
A8: 車名 | B8: =[1]顧客名簿!$D$4 -> スズキエヴリィ | F8: 登録番号T7-8106-7609-0169
A9: 型式・年式 | B9: =[1]顧客名簿!$D$7 -> 15133 | F9: 振込口座 西中国信用金庫
A10: ナンバー | B10: =[1]顧客名簿!$D$5 -> 下関580り7 | F10: 一の宮支店 普通 0341746
A11: 車台番号 | B11: =[1]顧客名簿!$D$6 -> DA64W-248979 | F11: 大平自動車商会 ｵｵﾋﾗ ﾋﾃﾞｱｷ
A13: ご請求金額 | B13: =G38 -> 0
A15: 商品名 | B15: 適用 | C15: 数量 | D15: 単価(税抜） | E15: 消費税率 | F15: 税額 | G15: 金額(税抜)
F16: =C16*D16*E16 -> 0 | G16: =D16*C16 -> 0
F17: =C17*D17*E17 -> 0 | G17: =D17*C17 -> 0
F18: =C18*D18*E18 -> 0 | G18: =D18*C18 -> 0
F19: =C19*D19*E19 -> 0 | G19: =D19*C19 -> 0
F20: =C20*D20*E20 -> 0 | G20: =D20*C20 -> 0
F21: =C21*D21*E21 -> 0 | G21: =D21*C21 -> 0
F22: =C22*D22*E22 -> 0 | G22: =D22*C22 -> 0
F23: =C23*D23*E23 -> 0 | G23: =D23*C23 -> 0
F24: =C24*D24*E24 -> 0 | G24: =D24*C24 -> 0
F25: =C25*D25*E25 -> 0 | G25: =D25*C25 -> 0
F26: =C26*D26*E26 -> 0 | G26: =D26*C26 -> 0
F27: =C27*D27*E27 -> 0 | G27: =D27*C27 -> 0
... F35: =C35*D35*E35 -> 0 | G35: =D35*C35 -> 0
A36: ※ｵｰﾀﾞｰ商品は返品できない場合があります。 | E36: 商品代金 | G36: =SUM(G16:H35) -> 0
E37: 消費税(10％) | G37: =SUM(F16:F35) -> 0
E38: 合計 | G38: =SUM(G36:H37) -> 0

Sheet 売上集計用
A1: 御請求日 | B1: お客様名 | C1: 住所1 | D1: 住所2 | E1: T E L | F1: 車名 | G1: 型式・年式 | H1: ナンバー | I1: 車台番号 | J1: 商品代金 | K1: 消費税(10％) | L1: ご請求金額
A2: =請求書!G2 -> 0 | B2: =請求書!B3 -> 山本 剛 | C2: =請求書!B4 -> 山口県下関市田倉 | D2: =請求書!B5 -> 125-5 | E2: =請求書!B6 -> 090-9061-7286 | F2: =請求書!B8 -> スズキエヴリィ | G2: =請求書!B9 -> 15133 | H2: =請求書!B10 -> 下関580り7 | I2: =請求書!B11 -> DA64W-248979 | J2: =請求書!G36 -> 0 | K2: =請求書!G37 -> 0 | L2: =請求書!G38 -> 0
